License.md
csc/__init__.py
csc/__main__.py
csc/_cli.py
csc/_script.py
csc-24.2.0.dist-info/METADATA
csc-24.2.0.dist-info/WHEEL
csc-24.2.0.dist-info/RECORD
