Metadata-Version: 2.1
Name: csc
Version: 24.2.0
Summary: Execute python scripts cell by cell  
License: MIT
Author: Christopher Prohm
Author-email: mail@cprohm.de
Requires-Python: >=3.8,<4
Classifier: Intended Audience :: Developers
Classifier: License :: OSI Approved :: MIT License
Classifier: Programming Language :: Python :: 3
Classifier: Programming Language :: Python :: 3.8
Classifier: Programming Language :: Python :: 3.9
Classifier: Programming Language :: Python :: 3.10
Classifier: Programming Language :: Python :: 3.11
Classifier: Programming Language :: Python :: 3.12
